lightweight_charts_v5/__init__.py
lightweight_charts_v5/frontend/build/asset-manifest.json
lightweight_charts_v5/frontend/build/bootstrap.min.css
lightweight_charts_v5/frontend/build/index.html
lightweight_charts_v5/frontend/build/static/js/main.f8e5d372.js
lightweight_charts_v5/frontend/build/static/js/main.f8e5d372.js.LICENSE.txt
lightweight_charts_v5/frontend/build/static/js/main.f8e5d372.js.map
streamlit_lightweight_charts_v5-0.1.8.dist-info/METADATA
streamlit_lightweight_charts_v5-0.1.8.dist-info/WHEEL
streamlit_lightweight_charts_v5-0.1.8.dist-info/top_level.txt
streamlit_lightweight_charts_v5-0.1.8.dist-info/RECORD
