Metadata-Version: 2.4
Name: streamlit-lightweight-charts-v5
Version: 0.1.8
Summary: Streamlit component for viewing v5 Lightweight Charts
Author-email: Urban Ottosson <urban@ottosson.org>
License-Expression: MIT
Project-URL: Homepage, https://github.com/locupleto/streamlit-lightweight-charts-v5
Classifier: Programming Language :: Python :: 3
Classifier: Operating System :: OS Independent
Requires-Python: >=3.7
Requires-Dist: streamlit>=0.63
Provides-Extra: devel
Requires-Dist: wheel; extra == "devel"
Requires-Dist: pytest==7.4.0; extra == "devel"
Requires-Dist: playwright==1.48.0; extra == "devel"
Requires-Dist: requests==2.31.0; extra == "devel"
Requires-Dist: pytest-playwright-snapshot==1.0; extra == "devel"
Requires-Dist: pytest-rerunfailures==12.0; extra == "devel"
Provides-Extra: demo
Requires-Dist: yfinance; extra == "demo"
Requires-Dist: numpy; extra == "demo"
